[
  {
    "inter": {
      "time": "2016-04-09T19:02:11.471480658585Z",
      "lat": 28.53650501,
      "fixFrac": 14.49429613171781,
      "lng": -81.84553486,
      "alt": 138.35
    },
    "cross": {
      "inZone": [
        true,
        false
      ],
      "crossingPair": [
        {
          "time": "2016-04-09T19:02:09Z",
          "lat": 28.53621667,
          "fix": 14,
          "lng": -81.84566667,
          "alt": 125
        },
        {
          "time": "2016-04-09T19:02:14Z",
          "lat": 28.5368,
          "fix": 15,
          "lng": -81.8454,
          "alt": 152
        }
      ]
    }
  },
  {
    "inter": {
      "time": "2016-04-09T19:30:42.64423637494Z",
      "lat": 28.48783952,
      "fixFrac": 356.7288472749881,
      "lng": -81.84689379,
      "alt": 858.44
    },
    "cross": {
      "inZone": [
        true,
        false
      ],
      "crossingPair": [
        {
          "time": "2016-04-09T19:30:39Z",
          "lat": 28.48848333,
          "fix": 356,
          "lng": -81.84696667,
          "alt": 865
        },
        {
          "time": "2016-04-09T19:30:44Z",
          "lat": 28.4876,
          "fix": 357,
          "lng": -81.84686667,
          "alt": 856
        }
      ]
    }
  },
  {
    "inter": {
      "time": "2016-04-09T20:26:31.682326786605Z",
      "lat": 28.26121675,
      "fixFrac": 1026.536465357322,
      "lng": -81.82766874,
      "alt": 659.15
    },
    "cross": {
      "inZone": [
        false,
        true
      ],
      "crossingPair": [
        {
          "time": "2016-04-09T20:26:29Z",
          "lat": 28.26158333,
          "fix": 1026,
          "lng": -81.82788333,
          "alt": 657
        },
        {
          "time": "2016-04-09T20:26:34Z",
          "lat": 28.2609,
          "fix": 1027,
          "lng": -81.82748333,
          "alt": 661
        }
      ]
    }
  },
  {
    "inter": {
      "time": "2016-04-09T20:50:18.418980477765Z",
      "lat": 28.16081156,
      "fixFrac": 1311.883796095553,
      "lng": -81.80612909,
      "alt": 355.58
    },
    "cross": {
      "inZone": [
        false,
        true
      ],
      "crossingPair": [
        {
          "time": "2016-04-09T20:50:14Z",
          "lat": 28.16153333,
          "fix": 1311,
          "lng": -81.80635,
          "alt": 360
        },
        {
          "time": "2016-04-09T20:50:19Z",
          "lat": 28.16071667,
          "fix": 1312,
          "lng": -81.8061,
          "alt": 355
        }
      ]
    }
  }
]
