[
  {
    "inter": {
      "time": "2016-04-03T19:47:53.524054480985Z",
      "lat": 28.53643289,
      "fixFrac": 13.304810896197493,
      "lng": -81.8452803,
      "alt": 81.57
    },
    "cross": {
      "inZone": [
        true,
        false
      ],
      "crossingPair": [
        {
          "time": "2016-04-03T19:47:52Z",
          "lat": 28.53625,
          "fix": 13,
          "lng": -81.84536667,
          "alt": 77
        },
        {
          "time": "2016-04-03T19:47:57Z",
          "lat": 28.53685,
          "fix": 14,
          "lng": -81.84508333,
          "alt": 92
        }
      ]
    }
  },
  null,
  null,
  null
]
