[
  {
    "inter": {
      "time": "2016-04-06T17:31:52.3685798319Z",
      "lat": 28.5360837,
      "fixFrac": 14.036857983190389,
      "lng": -81.84450569
    },
    "cross": {
      "inZone": [
        true,
        false
      ],
      "crossingPair": [
        {
          "time": "2016-04-06T17:31:52Z",
          "lat": 28.53603333,
          "fix": 14,
          "lng": -81.84453333
        },
        {
          "time": "2016-04-06T17:32:02Z",
          "lat": 28.5374,
          "fix": 15,
          "lng": -81.84378333
        }
      ]
    }
  },
  {
    "inter": {
      "time": "2016-04-06T17:56:05.099404729848Z",
      "lat": 28.56301062,
      "fixFrac": 156.46358224816868,
      "lng": -81.88482142
    },
    "cross": {
      "inZone": [
        true,
        false
      ],
      "crossingPair": [
        {
          "time": "2016-04-06T17:56:00Z",
          "lat": 28.56293333,
          "fix": 156,
          "lng": -81.88403333
        },
        {
          "time": "2016-04-06T17:56:11Z",
          "lat": 28.5631,
          "fix": 157,
          "lng": -81.88573333
        }
      ]
    }
  },
  null,
  null
]
